{
  "updated_utc": "2026-06-24T20:01:46+00:00",
  "updated_th": "25 มิ.ย. 2569, 03:01 น.",
  "timeframe": "1H",
  "signals": [
    {
      "symbol": "BTC/USD",
      "signal": "SHORT",
      "confidence": 87,
      "price": 59858.28,
      "tp": 58491.3,
      "sl": 60678.47,
      "rsi": 28.1,
      "adx": 34.9,
      "reasons": [
        "เทรนด์ขาลง",
        "เทรนด์ใหญ่หนุน",
        "ADX 35 เทรนด์แข็ง",
        "RSI 28"
      ],
      "ai": {
        "score": -0.4,
        "label": "bearish",
        "reason": "ข่าวส่วนใหญ่ชี้ลง อาจหลุด 60,000"
      }
    },
    {
      "symbol": "ETH/USD",
      "signal": "SHORT",
      "confidence": 80,
      "price": 1582.69,
      "tp": 1535.44,
      "sl": 1611.04,
      "rsi": 28.5,
      "adx": 32.1,
      "reasons": [
        "เทรนด์ขาลง",
        "เทรนด์ใหญ่หนุน",
        "ADX 32 เทรนด์แข็ง",
        "RSI 29"
      ],
      "ai": {
        "score": -0.3,
        "label": "bearish",
        "reason": "ข่าวกังวล อาจดิ่งถึง 1,000"
      }
    },
    {
      "symbol": "USD/JPY",
      "signal": "NEUTRAL",
      "confidence": 46,
      "price": 161.83,
      "tp": null,
      "sl": null,
      "rsi": 63.8,
      "adx": 18.2,
      "reasons": [
        "เทรนด์ขาขึ้น",
        "ADX 18 ไซด์เวย์",
        "RSI 64"
      ],
      "ai": {
        "score": 0.5,
        "label": "bullish",
        "reason": "เยนอ่อนสุดรอบ 40 ปี"
      }
    },
    {
      "symbol": "XAU/USD",
      "signal": "SHORT",
      "confidence": 100,
      "price": 3988.62,
      "tp": 3929.09,
      "sl": 4024.34,
      "rsi": 32.1,
      "adx": 53.3,
      "reasons": [
        "เทรนด์ขาลง",
        "เทรนด์ใหญ่หนุน",
        "ADX 53 แรงมาก ระวังกลับตัว",
        "RSI 32"
      ],
      "ai": {
        "score": -0.6,
        "label": "bearish",
        "reason": "ทองหลุด 4,000 จุดต่ำสุดรอบ 7 เดือน"
      }
    }
  ]
}